mob_assistant/__init__.py
mob_assistant-0.2.0.dist-info/LICENSE
mob_assistant-0.2.0.dist-info/WHEEL
mob_assistant-0.2.0.dist-info/METADATA
mob_assistant-0.2.0.dist-info/RECORD
