Metadata-Version: 2.1
Name: mob-assistant
Version: 0.2.0
Summary: An assistant for mob programming.
Home-page: https://github.com/ddrexl/mob-assistant
License: MIT
Keywords: productivity,mob programming
Author: Dominik Drexl
Author-email: domdrexl@gmail.com
Requires-Python: >=3.6,<4.0
Classifier: License :: OSI Approved :: MIT License
Classifier: Programming Language :: Python :: 3
Classifier: Programming Language :: Python :: 3.6
Classifier: Programming Language :: Python :: 3.7
Project-URL: Repository, https://github.com/ddrexl/mob-assistant
